timecode/__init__.py
timecode-1.3.1.dist-info/LICENSE
timecode-1.3.1.dist-info/METADATA
timecode-1.3.1.dist-info/WHEEL
timecode-1.3.1.dist-info/top_level.txt
timecode-1.3.1.dist-info/zip-safe
timecode-1.3.1.dist-info/RECORD
