Metadata-Version: 2.1
Name: timecode
Version: 1.3.1
Summary: SMPTE Time Code Manipulation Library
Home-page: https://github.com/eoyilmaz/timecode
Author: ['Erkan Ozgur Yilmaz']
Author-email: ['eoyilmaz@gmail.com']
License: UNKNOWN
Keywords: video,timecode,smpte
Platform: UNKNOWN
Classifier: Programming Language :: Python
Classifier: License :: OSI Approved :: MIT License
Classifier: Operating System :: OS Independent
Classifier: Development Status :: 5 - Production/Stable
Classifier: Topic :: Software Development :: Libraries :: Python Modules
